AUTHORS
CHANGELOG.txt
DESCRIPTION
LICENSE
MANIFEST.in
README.rst
requirements.txt
runtests.py
setup.cfg
setup.py
test_requirements.txt
tox.ini
django_api_key/__init__.py
django_api_key/admin.py
django_api_key/middleware.py
django_api_key/models.py
django_api_key/urls.py
django_api_key/views.py
django_api_key.egg-info/PKG-INFO
django_api_key.egg-info/SOURCES.txt
django_api_key.egg-info/dependency_links.txt
django_api_key.egg-info/requires.txt
django_api_key.egg-info/top_level.txt
django_api_key/migrations/0001_initial.py
django_api_key/migrations/0002_ipaccess.py
django_api_key/migrations/__init__.py
django_api_key/static/.empty
django_api_key/static/drf_api_key/.empty
django_api_key/templates/drf_api_key/.empty
django_api_key/templatetags/__init__.py
django_api_key/templatetags/drf_api_key_tags.py
django_api_key/tests/__init__.py
django_api_key/tests/models_tests.py
django_api_key/tests/settings.py
django_api_key/tests/test_settings.py
django_api_key/tests/urls.py
django_api_key/tests/views.py
django_api_key/tests/test_app/__init__.py
django_api_key/tests/test_app/models.py
django_api_key/tests/test_app/templates/400.html
django_api_key/tests/test_app/templates/500.html