Metadata-Version: 2.1
Name: django-api-key
Version: 0.1.0
Summary: Per URL api-key control for Django
